.project-version
LICENSE
MANIFEST.in
README.md
setup.cfg
setup.py
project_version/__init__.py
project_version/abstarct.py
project_version/commands.py
project_version/constants.py
project_version/entrypoint.py
project_version/help.py
project_version/services.py
project_version/utils.py
project_version.egg-info/PKG-INFO
project_version.egg-info/SOURCES.txt
project_version.egg-info/dependency_links.txt
project_version.egg-info/entry_points.txt
project_version.egg-info/requires.txt
project_version.egg-info/top_level.txt
requirements/dev.txt
requirements/ops.txt
requirements/project.txt
requirements/tests.txt